migrator/__init__.py
migrator/configure.py
databasemigrator-0.0.2.dist-info/METADATA
databasemigrator-0.0.2.dist-info/WHEEL
databasemigrator-0.0.2.dist-info/entry_points.txt
databasemigrator-0.0.2.dist-info/top_level.txt
databasemigrator-0.0.2.dist-info/RECORD
