Metadata-Version: 2.1
Name: databasemigrator
Version: 0.0.2
Summary: Utility to help migration database, common use for docker containers
Home-page: UNKNOWN
Author: rafaelscone (Rafael Schneider)
Author-email: <databasemigrator@impaire.com>
License: UNKNOWN
Keywords: database,mysql,migrator
Platform: UNKNOWN
Classifier: Development Status :: 1 - Planning
Classifier: Intended Audience :: Developers
Classifier: Programming Language :: Python :: 3
Classifier: Operating System :: Unix
Classifier: Operating System :: MacOS :: MacOS X
Classifier: Operating System :: Microsoft :: Windows
Requires-Dist: dotenv
Requires-Dist: mysql.connector (==2.2.9)
